BarcodeGenerator/BarcodeGenerator.py
BarcodeGenerator/__init__.py
TextBarcodeGenerator-2022.0.2.dist-info/LICENSE
TextBarcodeGenerator-2022.0.2.dist-info/METADATA
TextBarcodeGenerator-2022.0.2.dist-info/WHEEL
TextBarcodeGenerator-2022.0.2.dist-info/top_level.txt
TextBarcodeGenerator-2022.0.2.dist-info/RECORD
